UnlimitedChatGPTWebAPI/__init__.py
UnlimitedChatGPTWebAPI/data.py
UnlimitedChatGPTWebAPI/session.py
UnlimitedChatGPTWebAPI/js/preload.js
UnlimitedChatGPTWebAPI-0.1.2.dist-info/LICENSE
UnlimitedChatGPTWebAPI-0.1.2.dist-info/METADATA
UnlimitedChatGPTWebAPI-0.1.2.dist-info/WHEEL
UnlimitedChatGPTWebAPI-0.1.2.dist-info/top_level.txt
UnlimitedChatGPTWebAPI-0.1.2.dist-info/RECORD
