Metadata-Version: 2.1
Name: UnlimitedChatGPTWebAPI
Version: 0.1.2
Summary: Unlimited ChatGPT WebAPI
Author-email: AkashiCoin <l1040186796@gmail.com>
License: MIT
Project-URL: Homepage, https://github.com/AkashiCoin/UnlimitedChatGPTWebAPI
Project-URL: Repository, https://github.com/AkashiCoin/UnlimitedChatGPTWebAPI
Requires-Python: >=3.8
License-File: LICENSE
Requires-Dist: playwright (>=1.28.0)
Requires-Dist: pydantic (>=1.9.0)
Requires-Dist: loguru (>=0.6.0)
